nlqcat/__init__.py
nlqcat/core/__init__.py
nlqcat/core/base_pipeline.py
nlqcat/core/ner.py
nlqcat/core/nlp_base.py
nlqcat/core/parser.py
nlqcat/core/pipeline.py
nlqcat/core/rag.py
nlqcat/core/tokenizer.py
nlqcat/core/utils.py
nlqcat/debug_db/chroma.sqlite3
nlqcat/debug_db/e38d8262-e439-4a33-90b5-341c3b8ece70/data_level0.bin
nlqcat/debug_db/e38d8262-e439-4a33-90b5-341c3b8ece70/header.bin
nlqcat/debug_db/e38d8262-e439-4a33-90b5-341c3b8ece70/length.bin
nlqcat/debug_db/e38d8262-e439-4a33-90b5-341c3b8ece70/link_lists.bin
nlqcat/models/huggingface_llm.py
nlqcat/models/llm_base.py
nlqcat/models/load_spacy.py
nlqcat/models/mock_llm.py
nlqcat/models/openai_llm.py
nlqcat/semantic/__init__.py
nlqcat/semantic/clustering.py
nlqcat/semantic/embedding.py
nlqcat/semantic/similarity.py
nlqcat/semantic/summarizer.py
nlqcat/vector_store/__init__.py
nlqcat/vector_store/base_vector_store.py
nlqcat/vector_store/chroma_store.py
nlqcat/vector_store/faiss_store.py
nlqcat/vector_store/pinecone_store.py
nlqcat-0.1.3.dist-info/licenses/LICENSE
nlqcat-0.1.3.dist-info/METADATA
nlqcat-0.1.3.dist-info/WHEEL
nlqcat-0.1.3.dist-info/top_level.txt
nlqcat-0.1.3.dist-info/RECORD
