Metadata-Version: 2.4
Name: nlqcat
Version: 0.1.3
Summary: Natural Language Question Answering Toolkit (Hybrid NLP + GenAI)
Author-email: Anirban Sarkar <sanirbansarkar@gmail.com>
Project-URL: Homepage, https://github.com/AnirbansarkarS/NLQcat
Classifier: Programming Language :: Python :: 3
Classifier: License :: OSI Approved :: MIT License
Classifier: Operating System :: OS Independent
Requires-Python: >=3.8
License-File: LICENSE
Requires-Dist: spacy>=3.0.0
Requires-Dist: chromadb>=0.4.0
Requires-Dist: sentence-transformers>=2.2.0
Requires-Dist: numpy
Provides-Extra: openai
Requires-Dist: openai>=1.0.0; extra == "openai"
Dynamic: license-file
